django_visit_count/__init__.py
django_visit_count/app_settings.py
django_visit_count/mixins.py
django_visit_count/utils.py
django_visit_count/locale/fa/LC_MESSAGES/django.mo
django_visit_count/locale/fa/LC_MESSAGES/django.po
django_visit_count-1.2.1.dist-info/LICENSE.txt
django_visit_count-1.2.1.dist-info/METADATA
django_visit_count-1.2.1.dist-info/WHEEL
django_visit_count-1.2.1.dist-info/top_level.txt
django_visit_count-1.2.1.dist-info/RECORD
